ocean_crow_qa_chat/__init__.py
ocean_crow_qa_chat/ocean_crow_qa_chat.py
ocean_crow_qa_chat-0.1.1.dist-info/licenses/LICENSE
ocean_crow_qa_chat-0.1.1.dist-info/METADATA
ocean_crow_qa_chat-0.1.1.dist-info/WHEEL
ocean_crow_qa_chat-0.1.1.dist-info/entry_points.txt
ocean_crow_qa_chat-0.1.1.dist-info/top_level.txt
ocean_crow_qa_chat-0.1.1.dist-info/RECORD
