Metadata-Version: 2.4
Name: ocean-crow-qa-chat
Version: 0.1.1
Summary: In-game developer-player Q&A system by OceanCrow
Author-email: Sheldon Kenny Salmon <OceanCrowtt@gmail.com>
License-Expression: MIT
Project-URL: Homepage, https://oceancrow.carrd.co
Project-URL: Repository, https://github.com/OceanCrow-TT/ocean_crow_qa_chat
Project-URL: Issues, https://github.com/OceanCrow-TT/ocean_crow_qa_chat/issues
Keywords: gaming,qa,pygame,ocean-crow
Classifier: Programming Language :: Python :: 3
Classifier: Operating System :: OS Independent
Requires-Python: >=3.9
License-File: LICENSE
Requires-Dist: pygame>=2.0.0
Provides-Extra: test
Requires-Dist: pytest>=7.0.0; extra == "test"
Dynamic: license-file
